LICENSE
MANIFEST.in
README.rst
setup.cfg
setup.py
pretix_mandatory_product/__init__.py
pretix_mandatory_product/apps.py
pretix_mandatory_product/signals.py
pretix_mandatory_product/urls.py
pretix_mandatory_product/views.py
pretix_mandatory_product.egg-info/PKG-INFO
pretix_mandatory_product.egg-info/SOURCES.txt
pretix_mandatory_product.egg-info/dependency_links.txt
pretix_mandatory_product.egg-info/entry_points.txt
pretix_mandatory_product.egg-info/requires.txt
pretix_mandatory_product.egg-info/top_level.txt
pretix_mandatory_product/locale/.gitkeep
pretix_mandatory_product/locale/de/LC_MESSAGES/django.po
pretix_mandatory_product/locale/de_informal/LC_MESSAGES/django.po
pretix_mandatory_product/static/pretix_force_product/.gitkeep
pretix_mandatory_product/templates/pretix_mandatory_product/.gitkeep
pretix_mandatory_product/templates/pretix_mandatory_product/settings.html
tests/test_checkout.py
tests/test_event_clone.py
tests/test_event_go_live.py
tests/test_signals.py