Metadata-Version: 2.1
Name: pretix-mandatory-product
Version: 1.3.0
Summary: Add questions to the contact info section
Home-page: https://github.com/bockstaller/pretix-mandatory-product
Author: Lukas Bockstaller
Author-email: lukas.bockstaller@posteo.de
License: Apache
License-File: LICENSE
Requires-Dist: pretix
Requires-Dist: Django
